rho_ml/__init__.py
rho_ml/rho_model.py
rho_ml/utils.py
rho_ml-0.2.0.dist-info/LICENSE
rho_ml-0.2.0.dist-info/METADATA
rho_ml-0.2.0.dist-info/WHEEL
rho_ml-0.2.0.dist-info/top_level.txt
rho_ml-0.2.0.dist-info/RECORD
