Metadata-Version: 2.1
Name: rho-ml
Version: 0.2.0
Summary: Standard framework for wrapping ML and other algorithms
Home-page: https://bitbucket.org/rhoai/rho-ml
Maintainer: Rho AI Corporation
License: Commercial
Platform: UNKNOWN
Classifier: Intended Audience :: Developers
Classifier: Intended Audience :: System Administrators
Classifier: License :: OSI Approved :: MIT License
Classifier: Operating System :: OS Independent
Classifier: Programming Language :: Python
Classifier: Programming Language :: Python :: 3
Classifier: Programming Language :: Python :: 3.3
Classifier: Programming Language :: Python :: 3.4
Classifier: Programming Language :: Python :: 3.5
Classifier: Programming Language :: Python :: 3.6
Classifier: Programming Language :: Python :: 3.7
Requires-Dist: attrs
Requires-Dist: marshmallow
Provides-Extra: dev
Requires-Dist: honcho ; extra == 'dev'
Provides-Extra: test
Requires-Dist: pytest ; extra == 'test'
Requires-Dist: tox ; extra == 'test'
Requires-Dist: coverage ; extra == 'test'
Requires-Dist: hypothesis ; extra == 'test'
